terminaide/__init__.py
terminaide/core/config.py
terminaide/core/cursor.py
terminaide/core/exceptions.py
terminaide/core/factory.py
terminaide/core/index.py
terminaide/core/installer.py
terminaide/core/logger.py
terminaide/core/models.py
terminaide/core/monitor.py
terminaide/core/proxy.py
terminaide/core/server.py
terminaide/core/terminal.py
terminaide/core/terminascii.py
terminaide/core/validator.py
terminaide/core/wrappers.py
terminaide/static/favicon.ico
terminaide/static/preview.png
terminaide/templates/index.html
terminaide/templates/terminal.html
terminarcade/__init__.py
terminarcade/asteroids.py
terminarcade/pong.py
terminarcade/snake.py
terminarcade/tetris.py
terminaide-1.4.5.dist-info/LICENSE
terminaide-1.4.5.dist-info/METADATA
terminaide-1.4.5.dist-info/WHEEL
terminaide-1.4.5.dist-info/RECORD
