Metadata-Version: 2.1
Name: terminaide
Version: 1.4.5
Summary: Serve Python CLI applications in the browser using ttyd
Home-page: https://github.com/basileaw/terminaide
License: MIT
Author: Alex Basile
Author-email: basileaw@gmail.com
Requires-Python: >=3.12,<4.0
Classifier: License :: OSI Approved :: MIT License
Classifier: Programming Language :: Python :: 3
Classifier: Programming Language :: Python :: 3.12
Classifier: Programming Language :: Python :: 3.13
Requires-Dist: bs4 (>=0.0.2,<0.0.3)
Requires-Dist: fastapi (>=0.117,<0.118)
Requires-Dist: h11 (>=0.16.0,<0.17.0)
Requires-Dist: httpcore (>=1.0.9,<2.0.0)
Requires-Dist: httpx (>=0.28.1,<0.29.0)
Requires-Dist: jinja2 (>=3.1.2,<4.0.0)
Requires-Dist: pydantic (>=2.4.2,<3.0.0)
Requires-Dist: readchar (>=4.2.1,<5.0.0)
Requires-Dist: rich (>=14.0.0,<15.0.0)
Requires-Dist: uvicorn (>=0.34.2,<0.35.0)
Requires-Dist: websockets (>=12.0,<13.0)
Project-URL: Repository, https://github.com/basileaw/terminaide
